[
  {
    "fecha": "08/11/2021",
    "tipo_producto": "Licuadora",
    "motivo": "Producto incompleto...",
    "estado": ""
  },
  {
    "fecha": "25/02/2022",
    "tipo_producto": "Bocina",
    "motivo": "Producto da침ado...",
    "estado": ""
  },
  {
    "fecha": "15/03/2022",
    "tipo_producto": "Aud칤fonos",
    "motivo": "Producto irrelevante...",
    "estado": ""
  },
  {
    "fecha": "08/11/2021",
    "tipo_producto": "Licuadora",
    "motivo": "Producto incompleto...",
    "estado": ""
  },
  {
    "fecha": "25/02/2022",
    "tipo_producto": "Bocina",
    "motivo": "Producto da침ado...",
    "estado": ""
  },
  {
    "fecha": "08/11/2021",
    "tipo_producto": "Licuadora",
    "motivo": "Producto incompleto...",
    "estado": "游릭"
  },
  {
    "fecha": "25/02/2022",
    "tipo_producto": "Bocina",
    "motivo": "Producto da침ado...",
    "estado": "游댮"
  }
]
